fastipy/__init__.py
fastipy/src/__init__.py
fastipy/src/classes/__init__.py
fastipy/src/classes/decorators_base.py
fastipy/src/classes/json_database.py
fastipy/src/classes/mailer.py
fastipy/src/classes/template_render.py
fastipy/src/constants/__init__.py
fastipy/src/constants/content_types.py
fastipy/src/constants/decorators.py
fastipy/src/constants/events.py
fastipy/src/constants/hooks.py
fastipy/src/constants/http_methods.py
fastipy/src/constants/http_status_code.py
fastipy/src/constants/serializers.py
fastipy/src/core/__init__.py
fastipy/src/core/fastipy.py
fastipy/src/core/reply.py
fastipy/src/core/request.py
fastipy/src/core/request_handler.py
fastipy/src/exceptions/__init__.py
fastipy/src/exceptions/decorator_already_exists_exception.py
fastipy/src/exceptions/duplicate_route_exception.py
fastipy/src/exceptions/exception_handler.py
fastipy/src/exceptions/fastipy_exception.py
fastipy/src/exceptions/file_exception.py
fastipy/src/exceptions/invalid_path_exception.py
fastipy/src/exceptions/no_event_type.py
fastipy/src/exceptions/no_hook_type.py
fastipy/src/exceptions/no_http_method_exception.py
fastipy/src/exceptions/plugin_exception.py
fastipy/src/exceptions/reply_exception.py
fastipy/src/helpers/__init__.py
fastipy/src/helpers/async_sync_helpers.py
fastipy/src/helpers/content_type.py
fastipy/src/helpers/route_helpers.py
fastipy/src/middlewares/__init__.py
fastipy/src/middlewares/cors.py
fastipy/src/models/__init__.py
fastipy/src/models/body.py
fastipy/src/models/file.py
fastipy/src/models/form.py
fastipy/src/routes/__init__.py
fastipy/src/routes/plugin_tree.py
fastipy/src/routes/router.py
fastipy/src/types/__init__.py
fastipy/src/types/fastipy.py
fastipy/src/types/plugins.py
fastipy/src/types/routes.py
fastipy-1.5.4.dist-info/LICENSE
fastipy-1.5.4.dist-info/METADATA
fastipy-1.5.4.dist-info/WHEEL
fastipy-1.5.4.dist-info/RECORD
