Metadata-Version: 2.1
Name: fastipy
Version: 1.5.4
Summary: Fastipy is a fast and easy-to-use open source Python library for developing RESTful APIs. Inspired by the FastAPI and Fastify syntax and powered by uvicorn ASGI web server.
Home-page: https://github.com/Bielgomes/Fastipy
License: GPLv3
Keywords: RESTful,API,ASGI,FastAPI,Fastipy,web server
Author: Bielgomes
Author-email: bielgomesdasilva@hotmail.com
Requires-Python: >=3.10.11,<4.0.0
Classifier: Development Status :: 4 - Beta
Classifier: Environment :: Web Environment
Classifier: Intended Audience :: Developers
Classifier: License :: OSI Approved :: GNU General Public License v3 (GPLv3)
Classifier: License :: Other/Proprietary License
Classifier: Operating System :: OS Independent
Classifier: Programming Language :: Python
Classifier: Programming Language :: Python :: 3
Classifier: Programming Language :: Python :: 3.11
Classifier: Programming Language :: Python :: 3.12
Classifier: Programming Language :: Python :: 3.13
Classifier: Programming Language :: Python :: 3.10
Classifier: Topic :: Internet :: WWW/HTTP
Classifier: Topic :: Internet :: WWW/HTTP :: Dynamic Content
Classifier: Topic :: Software Development :: Libraries :: Python Modules
Requires-Dist: httpx (>=0.27.2,<0.28.0)
Requires-Dist: jinja2 (>=3.1.4,<4.0.0)
Requires-Dist: nest-asyncio (>=1.6.0,<2.0.0)
Requires-Dist: starlette[standard] (>=0.41.2,<0.42.0)
Requires-Dist: uvicorn (>=0.32.0,<0.33.0)
Project-URL: Bug tracker, https://github.com/Bielgomes/fastipy/issues
Project-URL: Code, https://github.com/Bielgomes/fastipy
Project-URL: Repository, https://github.com/Bielgomes/Fastipy
